setup.cfg
setup.py
eventsource/__init__.py
eventsource/exceptions.py
eventsource/application/__init__.py
eventsource/application/base.py
eventsource/application/policies.py
eventsource/ext/__init__.py
eventsource/ext/inplaceactiverecordstrategy.py
eventsource/ext/pewee_active_record_strategy.py
eventsource/model/__init__.py
eventsource/model/aggregate.py
eventsource/model/decorators.py
eventsource/model/entity.py
eventsource/model/events.py
eventsource/model/snapshot.py
eventsource/services/__init__.py
eventsource/services/activerecord.py
eventsource/services/eventplayer.py
eventsource/services/eventsourcedrepository.py
eventsource/services/eventstore.py
eventsource/services/iterators.py
eventsource/services/sequenceditem.py
eventsource/services/sequenceditemmapper.py
eventsource/services/snapshotting.py
eventsource/services/time.py
eventsource/services/transcoding.py
eventsourcing_async.egg-info/PKG-INFO
eventsourcing_async.egg-info/SOURCES.txt
eventsourcing_async.egg-info/dependency_links.txt
eventsourcing_async.egg-info/not-zip-safe
eventsourcing_async.egg-info/requires.txt
eventsourcing_async.egg-info/top_level.txt
tests/__init__.py
tests/application.py
tests/application_tests.py
tests/db_tests.py
tests/domain_tests.py